parallel_processing/__init__.py
parallel_processing-0.1.5.dist-info/METADATA
parallel_processing-0.1.5.dist-info/WHEEL
parallel_processing-0.1.5.dist-info/RECORD
