Metadata-Version: 2.3
Name: parallel-processing
Version: 0.1.5
Summary: 
Author: Louis Nguyen
Author-email: louis.nguyen@qode.world
Requires-Python: >=3.10
Classifier: Programming Language :: Python :: 3
Classifier: Programming Language :: Python :: 3.10
Classifier: Programming Language :: Python :: 3.11
Classifier: Programming Language :: Python :: 3.12
Classifier: Programming Language :: Python :: 3.13
